codon/instrumentation/langgraph/__init__.py
codon/instrumentation/langgraph/adapter.py
codon/instrumentation/langgraph/attributes.py
codon/instrumentation/langgraph/callbacks.py
codon/instrumentation/langgraph/context.py
codon_instrumentation_langgraph-0.2.0a1.dist-info/licenses/LICENSE
codon_instrumentation_langgraph-0.2.0a1.dist-info/METADATA
codon_instrumentation_langgraph-0.2.0a1.dist-info/WHEEL
codon_instrumentation_langgraph-0.2.0a1.dist-info/top_level.txt
codon_instrumentation_langgraph-0.2.0a1.dist-info/RECORD
