Metadata-Version: 2.4
Name: codon-instrumentation-langgraph
Version: 0.2.0a1
Summary: Instrumentation package for LangGraph in the Codon ecosystem.
Author-email: "Codon, Inc." <martin@codonops.ai>, Sheldon Gilbert <sheldon@codonops.ai>, Martin Arroyo <martin@codonops.ai>
Maintainer-email: Martin Arroyo <martin@codonops.ai>, Carl Gordon <carl@codonops.ai>, Luis Moreno <luis@codonops.ai>
License: Apache-2.0
Project-URL: Homepage, https://codon-ops.github.io/codon-sdk/instrumentation/langgraph/
Project-URL: Bug Tracker, https://github.com/Codon-Ops/codon-sdk/issues
Project-URL: Documentation, https://codon-ops.github.io/codon-sdk/instrumentation/langgraph/
Classifier: Programming Language :: Python :: 3
Classifier: Development Status :: 3 - Alpha
Classifier: Operating System :: OS Independent
Requires-Python: >=3.9
License-File: LICENSE
Requires-Dist: codon-sdk
Requires-Dist: langchain>=1.0.0
Requires-Dist: langchain-core>=1.0.0
Requires-Dist: langgraph>=1.0.0
Requires-Dist: opentelemetry-api
Requires-Dist: opentelemetry-sdk
Requires-Dist: opentelemetry-exporter-otlp-proto-grpc
Dynamic: license-file
